[
    {
        "influencers": [
            {
                "name": "Lauren Drain",
                "handle": "@LAURENDRAINFIT"
            },
            {
                "name": "Massy Arias",
                "handle": "@MASSY.ARIAS"
            },
            {
                "name": "Jennifer Selter",
                "handle": "@JENSELTER"
            },
            {
                "name": "Nikki Blackletter",
                "handle": "@NIKKIBLACKLETTER"
            },
            {
                "name": "Michelle Lewin",
                "handle": "@MICHELLE_LEWIN"
            },
            {
                "name": "Sommer Ray",
                "handle": "@SOMMERRAY"
            }
        ]
    }
]