{
  "influencers": [
    {
      "name": "Lil Miquela",
      "handle": "",
      "handle_platform": ""
    },
    {
      "name": "Aitana López",
      "handle": "",
      "handle_platform": ""
    },
    {
      "name": "Noonoouri",
      "handle": "",
      "handle_platform": ""
    },
    {
      "name": "Imma",
      "handle": "",
      "handle_platform": ""
    },
    {
      "name": "Knox Frost",
      "handle": "",
      "handle_platform": ""
    },
    {
      "name": "Rozy",
      "handle": "",
      "handle_platform": ""
    },
    {
      "name": "Bermuda",
      "handle": "",
      "handle_platform": ""
    },
    {
      "name": "Shudu",
      "handle": "",
      "handle_platform": ""
    },
    {
      "name": "Milla Sofia",
      "handle": "",
      "handle_platform": ""
    },
    {
      "name": "Lu do Magalu",
      "handle": "",
      "handle_platform": ""
    }
  ]
}