[
    {
        "influencers": [
            {
                "name": "Sabrina Cesta",
                "handle": "@sabrinacesta"
            },
            {
                "name": "Emily Reyes | BuffButterfly🦋",
                "handle": "@emilyreyes__"
            },
            {
                "name": "Franccesca Sevilla | Catholic Women’s Fitness Coach ✝️",
                "handle": "@franccescasevilla"
            },
            {
                "name": "Joey Velázquez",
                "handle": "@greaserboyjoey"
            },
            {
                "name": "Alexis Xol",
                "handle": "@alexis_xol"
            },
            {
                "name": "Kristy",
                "handle": "@asap.kristy"
            },
            {
                "name": "Dulce Rodriguez 🇲🇽",
                "handle": "@sweetgainzzz"
            },
            {
                "name": "𝑪𝑹𝒀𝑺𝑻𝑨𝑳 𝑱𝑬𝑨𝑵 \"𝑮𝑼𝑨𝑴\"| 𝑶𝑵𝑳𝑰𝑵𝑬 𝑭𝑰𝑻𝑵𝑬𝑺𝑺 𝑪𝑶𝑨𝑪𝑯",
                "handle": "@grindwithguam"
            },
            {
                "name": "Samari C",
                "handle": "@only1samari"
            },
            {
                "name": "Tyler Wood",
                "handle": "@tylerjwwood"
            },
            {
                "name": "Shallamar Marchione",
                "handle": "@shallamar13"
            },
            {
                "name": "denver sean",
                "handle": "@just.denver"
            },
            {
                "name": "Desiree Van Nice",
                "handle": "@makinitdesirain"
            },
            {
                "name": "Cheri Wulff Lucas",
                "handle": "@cheri_wulff_lucas"
            },
            {
                "name": "Nikko Reyes",
                "handle": "@nikkoreyes"
            },
            {
                "name": "Lindsey",
                "handle": "@mzmaryjanee"
            },
            {
                "name": "Nayeli Maserati",
                "handle": "@nayelibelly.fit"
            },
            {
                "name": "Brandon Robles",
                "handle": "@yo_daddy_brandon"
            },
            {
                "name": "José Quintero",
                "handle": "@josequinterotv"
            },
            {
                "name": "Dustin Anderson",
                "handle": "@fitnessdust"
            }
        ]
    }
]